ftpfcs/__init__.py
ftpfcs/core.py
ftpfcs/utils.py
ftpfcs/__metadata__/DISCLIAIMER.md
ftpfcs/__metadata__/LICENSE
ftpfcs/__metadata__/README.md
ftpfcs/__metadata__/__init__.py
ftpfcs/__metadata__/requirements.txt
ftpfcs-0.0.9.dist-info/METADATA
ftpfcs-0.0.9.dist-info/WHEEL
ftpfcs-0.0.9.dist-info/top_level.txt
ftpfcs-0.0.9.dist-info/RECORD
